__init__.py
exporter.py
clickhouse_table_exporter-20240620.dist-info/LICENSE
clickhouse_table_exporter-20240620.dist-info/METADATA
clickhouse_table_exporter-20240620.dist-info/WHEEL
clickhouse_table_exporter-20240620.dist-info/top_level.txt
clickhouse_table_exporter-20240620.dist-info/RECORD
