Metadata-Version: 2.1
Name: clickhouse_table_exporter
Version: 20240620
Summary: A Python exporter for collecting clickhouse tables sizes.
Author-email: Alexey Antropov <alexeyantropov@gmail.com>
Project-URL: Homepage, https://github.com/alexeyantropov/clickhouse_table_exporter
Project-URL: Bug Tracker, https://github.com/alexeyantropov/clickhouse_table_exporter/issues
Classifier: Programming Language :: Python :: 3
Classifier: License :: OSI Approved :: MIT License
Classifier: Operating System :: OS Independent
Requires-Python: >=3.7
License-File: LICENSE
Requires-Dist: clickhouse-connect >=0.6.7
Requires-Dist: prometheus-client >=0.17.1
